__init__.py
readme_check.py
readme_check-0.1.4.dist-info/LICENSE
readme_check-0.1.4.dist-info/METADATA
readme_check-0.1.4.dist-info/WHEEL
readme_check-0.1.4.dist-info/top_level.txt
readme_check-0.1.4.dist-info/RECORD
