Metadata-Version: 2.1
Name: readme_check
Version: 0.1.4
Summary: Used to check readme
Author-email: Vishnu Venkatesh <vishnuchidambaranvenkatesh@gmail.com>
Classifier: Programming Language :: Python :: 3
Classifier: License :: OSI Approved :: MIT License
Classifier: Operating System :: OS Independent
Requires-Python: >=3.10
License-File: LICENSE
Requires-Dist: colorama ==0.4.6
